pepenc/__init__.py
pepenc/pepenc_utils.py
pepenc/data/__init__.py
pepenc/data/data_utils.py
pepenc/data/peptide_encoder_training_dataset.py
pepenc/data/conf/base/config.yaml
pepenc/data/intermediate/oh-aa-encoding-map.jpkl
pepenc/data/raw/sample-peptides.test.csv
pepenc/data/raw/sample-peptides.training.csv
pepenc/data/raw/sample-peptides.validation.csv
pepenc/models/__init__.py
pepenc/models/peptide_encoder_lstm_model.py
pepenc/models/peptide_encoder_lstm_net.py
pepenc/models/train_pepenc_models.py
peptide_encoder-0.2.2.dist-info/LICENSE
peptide_encoder-0.2.2.dist-info/METADATA
peptide_encoder-0.2.2.dist-info/WHEEL
peptide_encoder-0.2.2.dist-info/entry_points.txt
peptide_encoder-0.2.2.dist-info/top_level.txt
peptide_encoder-0.2.2.dist-info/RECORD
