Metadata-Version: 2.1
Name: peptide-encoder
Version: 0.2.2
Summary: An encoder for peptides (short amino acid sequences) based on BLOSUM similarity.
Home-page: https://github.com/bmmalone/peptide-encoder
Author: Brandon Malone
Author-email: bmmalone@gmail.com
License: MIT
Keywords: peptide encoding blossum
Platform: UNKNOWN
Classifier: Development Status :: 3 - Alpha
Classifier: Intended Audience :: Developers
Classifier: Intended Audience :: Science/Research
Classifier: License :: OSI Approved :: MIT License
Classifier: Natural Language :: English
Classifier: Programming Language :: Python :: 3 :: Only
Classifier: Topic :: Scientific/Engineering :: Artificial Intelligence
License-File: LICENSE
Requires-Dist: joblib
Requires-Dist: numpy
Requires-Dist: lifesci
Requires-Dist: pyllars
Requires-Dist: tqdm
Requires-Dist: pandas
Requires-Dist: pyyaml
Requires-Dist: ray[tune]
Requires-Dist: torch
Requires-Dist: gym
Requires-Dist: dm-tree
Requires-Dist: opencv-python
Provides-Extra: all
Requires-Dist: pytest ; extra == 'all'
Requires-Dist: coverage ; extra == 'all'
Requires-Dist: pytest-cov ; extra == 'all'
Requires-Dist: coveralls ; extra == 'all'
Requires-Dist: pytest-runner ; extra == 'all'
Requires-Dist: sphinx ; extra == 'all'
Requires-Dist: sphinx-rtd-theme ; extra == 'all'
Provides-Extra: docs
Requires-Dist: sphinx ; extra == 'docs'
Requires-Dist: sphinx-rtd-theme ; extra == 'docs'
Provides-Extra: gpu
Provides-Extra: test
Requires-Dist: pytest ; extra == 'test'
Requires-Dist: coverage ; extra == 'test'
Requires-Dist: pytest-cov ; extra == 'test'
Requires-Dist: coveralls ; extra == 'test'
Requires-Dist: pytest-runner ; extra == 'test'
